psfmachine/__init__.py
psfmachine/aperture.py
psfmachine/ffi.py
psfmachine/machine.py
psfmachine/perturbation.py
psfmachine/superstamp.py
psfmachine/tpf.py
psfmachine/utils.py
psfmachine/version.py
psfmachine-1.1.4.dist-info/LICENSE
psfmachine-1.1.4.dist-info/METADATA
psfmachine-1.1.4.dist-info/WHEEL
psfmachine-1.1.4.dist-info/RECORD
