Metadata-Version: 2.1
Name: psfmachine
Version: 1.1.4
Summary: Tool to perform fast PSF photometry of primary and background targets from Kepler/K2 Target Pixel Files
Home-page: https://ssdatalab.github.io/psfmachine/
License: MIT
Keywords: NASA, Kepler, Astronomy
Author: Christina Hedges
Author-email: christina.l.hedges@nasa.gov
Requires-Python: >=3.8,<4.0
Classifier: Intended Audience :: Science/Research
Classifier: License :: OSI Approved :: MIT License
Classifier: Programming Language :: Python :: 3
Classifier: Programming Language :: Python :: 3.8
Classifier: Programming Language :: Python :: 3.9
Classifier: Programming Language :: Python :: 3.10
Classifier: Programming Language :: Python :: 3.11
Classifier: Topic :: Scientific/Engineering :: Astronomy
Requires-Dist: astropy (>=5.2,<6.0)
Requires-Dist: corner (>=2.1.0,<3.0.0)
Requires-Dist: diskcache (>=5.3.0,<6.0.0)
Requires-Dist: fbpca (>=1.0,<2.0)
Requires-Dist: fitsio (>=1.1.3,<2.0.0)
Requires-Dist: imageio (>=2.9.0,<3.0.0)
Requires-Dist: imageio-ffmpeg (>=0.4.5,<0.5.0)
Requires-Dist: ipywidgets (>=7.6.3,<8.0.0)
Requires-Dist: jedi (==0.17.2)
Requires-Dist: kbackground (>=0.1.9,<0.2.0)
Requires-Dist: lightkurve (>=2.0.4,<3.0.0)
Requires-Dist: matplotlib (>=3.3.3,<4.0.0)
Requires-Dist: numpy (>=1.19.4,<2.0.0)
Requires-Dist: pandas (>=1.1,<2.0)
Requires-Dist: patsy (>=0.5.1,<0.6.0)
Requires-Dist: photutils (>=1.1.0,<2.0.0)
Requires-Dist: pyia (>=1.2,<2.0)
Requires-Dist: scipy (>=1.5.4,<2.0.0)
Requires-Dist: tqdm (>=4.54.0,<5.0.0)
Project-URL: Repository, https://github.com/ssdatalab/psfmachine
